google/cloud/dialogflowcx/__init__.py
google/cloud/dialogflowcx/gapic_version.py
google/cloud/dialogflowcx/py.typed
google/cloud/dialogflowcx_v3/__init__.py
google/cloud/dialogflowcx_v3/gapic_metadata.json
google/cloud/dialogflowcx_v3/gapic_version.py
google/cloud/dialogflowcx_v3/py.typed
google/cloud/dialogflowcx_v3/services/__init__.py
google/cloud/dialogflowcx_v3/services/agents/__init__.py
google/cloud/dialogflowcx_v3/services/agents/async_client.py
google/cloud/dialogflowcx_v3/services/agents/client.py
google/cloud/dialogflowcx_v3/services/agents/pagers.py
google/cloud/dialogflowcx_v3/services/agents/transports/__init__.py
google/cloud/dialogflowcx_v3/services/agents/transports/base.py
google/cloud/dialogflowcx_v3/services/agents/transports/grpc.py
google/cloud/dialogflowcx_v3/services/agents/transports/grpc_asyncio.py
google/cloud/dialogflowcx_v3/services/agents/transports/rest.py
google/cloud/dialogflowcx_v3/services/agents/transports/rest_base.py
google/cloud/dialogflowcx_v3/services/changelogs/__init__.py
google/cloud/dialogflowcx_v3/services/changelogs/async_client.py
google/cloud/dialogflowcx_v3/services/changelogs/client.py
google/cloud/dialogflowcx_v3/services/changelogs/pagers.py
google/cloud/dialogflowcx_v3/services/changelogs/transports/__init__.py
google/cloud/dialogflowcx_v3/services/changelogs/transports/base.py
google/cloud/dialogflowcx_v3/services/changelogs/transports/grpc.py
google/cloud/dialogflowcx_v3/services/changelogs/transports/grpc_asyncio.py
google/cloud/dialogflowcx_v3/services/changelogs/transports/rest.py
google/cloud/dialogflowcx_v3/services/changelogs/transports/rest_base.py
google/cloud/dialogflowcx_v3/services/deployments/__init__.py
google/cloud/dialogflowcx_v3/services/deployments/async_client.py
google/cloud/dialogflowcx_v3/services/deployments/client.py
google/cloud/dialogflowcx_v3/services/deployments/pagers.py
google/cloud/dialogflowcx_v3/services/deployments/transports/__init__.py
google_cloud_dialogflow_cx-1.43.0.dist-info/licenses/LICENSE
google_cloud_dialogflow_cx-1.43.0.dist-info/METADATA
google_cloud_dialogflow_cx-1.43.0.dist-info/WHEEL
google_cloud_dialogflow_cx-1.43.0.dist-info/top_level.txt
google_cloud_dialogflow_cx-1.43.0.dist-info/RECORD
